{"index.md":"BNiwo-7Y","pages_benchmarking.md":"DXGlBxTP","pages_builder.md":"lWBsw74e","pages_cli.md":"B1rufzLY","pages_codeanalysis.md":"BJtwhLwU","pages_configuration.md":"D8Bi9CSe","pages_essupport.md":"B6T5eQo5","pages_extensibility_customservermiddleware.md":"B5V2BYIZ","pages_extensibility_customtasks.md":"Cs7fbEeD","pages_extensibility_projectshims.md":"BiZ_ehuD","pages_faq.md":"BGRv9ul-","pages_filesystem.md":"Dh5GWqld","pages_gettingstarted.md":"D8y5Oi49","pages_openui5.md":"CtDRMS28","pages_overview.md":"CbSY4Hjm","pages_privacy.md":"CSOIvfWk","pages_project.md":"wpBQPP_C","pages_sapui5.md":"CzV6LcRm","pages_server.md":"B7SeHxKh","pages_troubleshooting.md":"C6imERE0","pages_workspace.md":"Dse2Zbxn","updates_migrate-v1.md":"CDlFq6K2","updates_migrate-v2.md":"Ch0Hnxi2","updates_migrate-v3.md":"vhIGpy60","updates_migrate-v4.md":"BhAkk4gJ","updates_migrate-v5.md":"CMvd0VnS"}
