{"index.md":"BX2l-23Y","pages_benchmarking.md":"DXGlBxTP","pages_builder.md":"D8rtsJda","pages_cli.md":"B1rufzLY","pages_codeanalysis.md":"hfXQhXlR","pages_configuration.md":"CSWW-duS","pages_essupport.md":"DR6WB5BO","pages_extensibility_customservermiddleware.md":"BvH_mpO3","pages_extensibility_customtasks.md":"BzuWZ_9d","pages_extensibility_projectshims.md":"BiZ_ehuD","pages_faq.md":"BGRv9ul-","pages_filesystem.md":"BDlhKCV3","pages_gettingstarted.md":"BK-4jrzC","pages_openui5.md":"CtDRMS28","pages_overview.md":"CbSY4Hjm","pages_privacy.md":"CSOIvfWk","pages_project.md":"B0ib-zo-","pages_sapui5.md":"CzV6LcRm","pages_server.md":"bDiSvIFc","pages_troubleshooting.md":"C6imERE0","pages_workspace.md":"Dse2Zbxn","updates_migrate-v1.md":"CDlFq6K2","updates_migrate-v2.md":"Ch0Hnxi2","updates_migrate-v3.md":"BNuZgwFw","updates_migrate-v4.md":"CEf68pku","updates_migrate-v5.md":"Ba32wb3C"}
